async_injector/__init__.py
async_injector/errors.py
async_injector/injector.py
async_injector/provider.py
async_injector/util.py
async_injector-0.1.0.dist-info/LICENSE
async_injector-0.1.0.dist-info/WHEEL
async_injector-0.1.0.dist-info/METADATA
async_injector-0.1.0.dist-info/RECORD
