Metadata-Version: 2.1
Name: async-injector
Version: 0.1.0
Summary: Dependency injector for modern Python
License: BSD
Author: Marcin Baczyński
Author-email: dev@mail.of.ninja
Requires-Python: >=3.9,<4.0
Classifier: License :: Other/Proprietary License
Classifier: Programming Language :: Python :: 3
Classifier: Programming Language :: Python :: 3.9
